oxifish-0.1.1.dist-info/METADATA
oxifish-0.1.1.dist-info/WHEEL
oxifish-0.1.1.dist-info/licenses/LICENSE
oxifish.libs/libgcc_s-39080030.so.1
oxifish/__init__.py
oxifish/__init__.pyi
oxifish/_oxifish.cpython-312-aarch64-linux-musl.so
oxifish/py.typed
oxifish-0.1.1.dist-info/RECORD
