Metadata-Version: 2.4
Name: oxifish
Version: 0.1.1
Classifier: Development Status :: 4 - Beta
Classifier: Intended Audience :: Developers
Classifier: License :: OSI Approved :: MIT License
Classifier: Programming Language :: Python :: 3
Classifier: Programming Language :: Python :: 3.11
Classifier: Programming Language :: Python :: 3.12
Classifier: Programming Language :: Python :: 3.13
Classifier: Programming Language :: Python :: 3.14
Classifier: Programming Language :: Rust
Classifier: Topic :: Security :: Cryptography
Classifier: Typing :: Typed
License-File: LICENSE
Summary: Python bindings for the RustCrypto Twofish block cipher implementation
Keywords: twofish,encryption,cipher,keepass,cryptography
Author: Corey Leavitt
License: MIT
Requires-Python: >=3.11
Project-URL: Homepage, https://github.com/coreyleavitt/oxifish
Project-URL: Repository, https://github.com/coreyleavitt/oxifish
Project-URL: Issues, https://github.com/coreyleavitt/oxifish/issues
